jupyterlab_dash/__init__.py
jupyterlab_dash/__version__.py
jupyterlab_dash-0.1.0a3.dist-info/LICENSE.txt
jupyterlab_dash-0.1.0a3.dist-info/METADATA
jupyterlab_dash-0.1.0a3.dist-info/WHEEL
jupyterlab_dash-0.1.0a3.dist-info/top_level.txt
jupyterlab_dash-0.1.0a3.dist-info/RECORD
