Metadata-Version: 2.1
Name: jupyterlab-dash
Version: 0.1.0a3
Summary: A JupyterLab extensions for rendering Plotly Dash apps
Home-page: https://github.com/plotly/jupyterlab-dash
Author: Plotly
License: MIT
Platform: UNKNOWN
Classifier: License :: OSI Approved :: MIT License
Classifier: Programming Language :: Python
Classifier: Programming Language :: Python :: 3
Classifier: Programming Language :: Python :: 3.5
Classifier: Programming Language :: Python :: 3.6
Classifier: Programming Language :: Python :: Implementation :: CPython
Requires-Python: >=3.5.0
